bad_units/__init__.py
bad_units/builtin_units.py
bad_units/module.py
bad_units-0.3.1.dist-info/licenses/LICENSE
bad_units-0.3.1.dist-info/METADATA
bad_units-0.3.1.dist-info/WHEEL
bad_units-0.3.1.dist-info/top_level.txt
bad_units-0.3.1.dist-info/RECORD
