Metadata-Version: 2.4
Name: bad-units
Version: 0.3.1
Summary: Very, very bad unit system for Python
Home-page: https://github.com/jacklaktimeishere/bad-units
Author: jacklak
Author-email: jacklakity@protonmail.com
Classifier: Programming Language :: Python :: 3
Classifier: License :: OSI Approved :: MIT License
Classifier: Operating System :: OS Independent
Requires-Python: >=3.7
License-File: LICENSE
Dynamic: license-file
